nobodd/__init__.py
nobodd/config.py
nobodd/default.conf
nobodd/disk.py
nobodd/fat.py
nobodd/fs.py
nobodd/gpt.py
nobodd/lang.py
nobodd/mbr.py
nobodd/netascii.py
nobodd/path.py
nobodd/prep.py
nobodd/server.py
nobodd/systemd.py
nobodd/tftp.py
nobodd/tftpd.py
nobodd/tools.py
nobodd-0.4.dist-info/LICENSE.txt
nobodd-0.4.dist-info/METADATA
nobodd-0.4.dist-info/WHEEL
nobodd-0.4.dist-info/entry_points.txt
nobodd-0.4.dist-info/top_level.txt
nobodd-0.4.dist-info/RECORD
