Metadata-Version: 2.1
Name: nobodd
Version: 0.4
Summary: A simple TFTP boot server for the Raspberry Pi
Author: Dave Jones
Author-email: dave.jones@canonical.com
Project-URL: Documentation, https://nobodd.readthedocs.io/
Project-URL: Source Code, https://github.com/waveform80/nobodd
Project-URL: Issue Tracker, https://github.com/waveform80/nobodd/issues
Keywords: raspberry pi boot nbd tftp
Classifier: Development Status :: 4 - Beta
Classifier: Environment :: Console
Classifier: Intended Audience :: System Administrators
Classifier: License :: OSI Approved :: GNU General Public License v3 (GPLv3)
Classifier: Operating System :: POSIX :: Linux
Classifier: Programming Language :: Python
Classifier: Programming Language :: Python :: 3
Classifier: Programming Language :: Python :: 3.7
Classifier: Programming Language :: Python :: 3.8
Classifier: Programming Language :: Python :: 3.9
Classifier: Programming Language :: Python :: 3.10
Classifier: Programming Language :: Python :: 3.11
Classifier: Programming Language :: Python :: 3.12
Classifier: Topic :: System :: Boot
Requires-Python: >=3.7
License-File: LICENSE.txt
Requires-Dist: setuptools
Requires-Dist: importlib-metadata (~=1.4) ; python_version < "3.8"
Requires-Dist: importlib-resources (~=1.3) ; python_version < "3.9"
Provides-Extra: doc
Requires-Dist: sphinx ; extra == 'doc'
Requires-Dist: sphinx-rtd-theme ; extra == 'doc'
Provides-Extra: test
Requires-Dist: pytest ; extra == 'test'
Requires-Dist: pytest-cov ; extra == 'test'
